{"hash":"598cb2497ad891189196726f5d918bc5b3b3ca75","data":{"docs":{"title":"Show parameters select all text | Bold Reports","date":"May 24, 2022","content":"\r\n## Is it possible to showing the selected all text instead of showing all values from a parameter\r\n\r\nYes, you can able to show the **Selected All** text instead of showing all values from parameter when we choose the select all option in Parameter using expression. You can find the below expression for achieving this.\r\n\r\n```csharp\r\n =iif(Parameters!<ParameterName>.Count == Count(Fields!<FieldName>.Value,\"<DatasetName>\"), \"Selected All\",Join(Parameters!<ParameterName>.value,\",\"))\r\n```","description":"This document provides the details for showing the selected all text instead of showing all values from a parameter"}},"context":{}}